migu_music_dl/__init__.py
migu_music_dl/cli.py
migu_music_dl/core.py
migu_music_dl/extenral_api.py
migu_music_dl-0.1.2.dist-info/entry_points.txt
migu_music_dl-0.1.2.dist-info/LICENSE
migu_music_dl-0.1.2.dist-info/WHEEL
migu_music_dl-0.1.2.dist-info/METADATA
migu_music_dl-0.1.2.dist-info/RECORD
